README.md
setup.py
pyTails.egg-info/PKG-INFO
pyTails.egg-info/SOURCES.txt
pyTails.egg-info/dependency_links.txt
pyTails.egg-info/entry_points.txt
pyTails.egg-info/top_level.txt
pytails/__init__.py
pytails/pytails.py
pytails/helpers/__init__.py
pytails/helpers/bson_utils.py
pytails/mongo/__init__.py
pytails/mongo/cdc_client.py
pytails/mongo/oplog_client.py
pytails/mongo/tail_client.py
pytails/sinks/__init__.py
pytails/sinks/console.py
pytails/sinks/firehose.py
pytails/sinks/kinesis.py
pytails/sinks/sink.py
pytails/state/__init__.py
pytails/state/ddb_store.py
pytails/state/null_store.py
pytails/state/store.py
tests/__init__.py
tests/test_helpers_bson_utils.py
webapp/__init__.py
webapp/app.py